config_manager/__init__.py
config_manager/config.py
config_manager/variable_parsers.py
config_manager_evjeny-0.3.0.dist-info/METADATA
config_manager_evjeny-0.3.0.dist-info/WHEEL
config_manager_evjeny-0.3.0.dist-info/top_level.txt
config_manager_evjeny-0.3.0.dist-info/RECORD
