Metadata-Version: 2.1
Name: config-manager-evjeny
Version: 0.3.0
Summary: Small config manager for parsing configs from different sources
Home-page: https://github.com/evjeny/config_manager
Author: evjeny
Author-email: gkanafing@gmail.com
License: UNKNOWN
Platform: UNKNOWN
Classifier: Programming Language :: Python :: 3
Classifier: License :: OSI Approved :: MIT License
Classifier: Operating System :: OS Independent
Requires-Python: >=3.7
